<?xml version="1.0" encoding="utf-8" ?><dwsync><file name="1column.phtml" server="208.86.153.244/public_html/upgrade/" local="3411347513" remote="16296245748" /><file name="2columns-left.phtml" server="208.86.153.244/public_html/upgrade/" local="3411604259" remote="16296502548" /><file name="2columns-right.phtml" server="208.86.153.244/public_html/upgrade/" local="3412464360" remote="16297366248" /><file name="3columns.phtml" server="208.86.153.244/public_html/upgrade/" local="3411347510" remote="16296245808" /><file name="empty.phtml" server="208.86.153.244/public_html/upgrade/" local="3410480820" remote="16295382708" /><file name="popup.phtml" server="208.86.153.244/public_html/upgrade/" local="3410480820" remote="16295382708" /><file name="print.phtml" server="208.86.153.244/public_html/upgrade/" local="3410480820" remote="16295382708" /><file name="redirect.phtml" server="208.86.153.244/public_html/upgrade/" local="3410480820" remote="16295382708" /></dwsync>